appcore/__init__.py
appcore/__main__.py
appcore/application.py
appcore/asyncf.py
appcore/cli.py
appcore/configuration.py
appcore/dictedits.py
appcore/distribution.py
appcore/environment.py
appcore/exceptions.py
appcore/generics.py
appcore/inscription.py
appcore/introspection.py
appcore/io.py
appcore/preparation.py
appcore/py.typed
appcore/state.py
appcore/__/__init__.py
appcore/__/imports.py
appcore/__/nomina.py
emcd_appcore-1.6.dist-info/METADATA
emcd_appcore-1.6.dist-info/WHEEL
emcd_appcore-1.6.dist-info/entry_points.txt
emcd_appcore-1.6.dist-info/licenses/LICENSE.txt
emcd_appcore-1.6.dist-info/RECORD
