Metadata-Version: 2.4
Name: emcd-appcore
Version: 1.6
Summary: Common application configuration management.
Project-URL: Homepage, https://github.com/emcd/python-appcore
Project-URL: Documentation, https://emcd.github.io/python-appcore
Project-URL: Download, https://pypi.org/project/emcd-appcore/#files
Project-URL: Source Code, https://github.com/emcd/python-appcore
Project-URL: Issue Tracker, https://github.com/emcd/python-appcore/issues
Author-email: Eric McDonald <emcd@users.noreply.github.com>
License-Expression: Apache-2.0
License-File: LICENSE.txt
Keywords: application,async,configuration
Classifier: Development Status :: 5 - Production/Stable
Classifier: Intended Audience :: Developers
Classifier: License :: OSI Approved :: Apache Software License
Classifier: Programming Language :: Python :: 3 :: Only
Classifier: Programming Language :: Python :: 3.10
Classifier: Programming Language :: Python :: 3.11
Classifier: Programming Language :: Python :: 3.12
Classifier: Programming Language :: Python :: 3.13
Classifier: Programming Language :: Python :: Implementation :: CPython
Classifier: Programming Language :: Python :: Implementation :: PyPy
Classifier: Topic :: Software Development
Requires-Python: >=3.10
Requires-Dist: absence~=1.1
Requires-Dist: aiofiles~=24.1.0
Requires-Dist: dynadoc~=1.4
Requires-Dist: exceptiongroup~=1.3.0
Requires-Dist: frigid~=4.2
Requires-Dist: icecream-truck~=1.5
Requires-Dist: importlib-metadata~=8.7.0
Requires-Dist: importlib-resources~=6.5.2
Requires-Dist: platformdirs~=4.4.0
Requires-Dist: python-dotenv~=1.1.1
Requires-Dist: tomli~=2.2.1
Requires-Dist: typing-extensions~=4.15.0
Provides-Extra: cli
Requires-Dist: rich~=13.0; extra == 'cli'
Requires-Dist: tomli-w~=1.2.0; extra == 'cli'
Requires-Dist: tyro~=0.9.0; extra == 'cli'
Provides-Extra: rich
Requires-Dist: rich; extra == 'rich'
